smltheory/__init__.py
smltheory/bayes_decision.py
smltheory/data/__init__.py
smltheory/data/data_best_in_class.csv
smltheory/data/data_bv_tradeoff.csv
smltheory/data/data_emp_loss.csv
smltheory/data/data_est_error.csv
smltheory/data/data_gen_error.csv
smltheory/data/data_opt_error_fast.csv
smltheory/datasets.py
smltheory/est_error.py
smltheory/generate_data.py
smltheory/gradient_descent.py
smltheory/least_squares.py
smltheory/opt_error.py
smltheory/overfitting.py
smltheory/trun_mvnt.py
smltheory-0.1.10.dist-info/LICENSE
smltheory-0.1.10.dist-info/METADATA
smltheory-0.1.10.dist-info/WHEEL
smltheory-0.1.10.dist-info/RECORD
