Metadata-Version: 2.1
Name: smltheory
Version: 0.1.10
Summary: Demonstrates propositions of supervised machine learning theories
License: MIT
Author: Sebastian Sciarra
Requires-Python: >=3.9,<3.13
Classifier: License :: OSI Approved :: MIT License
Classifier: Programming Language :: Python :: 3
Classifier: Programming Language :: Python :: 3.9
Classifier: Programming Language :: Python :: 3.10
Classifier: Programming Language :: Python :: 3.11
Requires-Dist: numpy (>=1.24.0,<2.0.0)
Requires-Dist: pandas (>=2.0.3)
Requires-Dist: scipy (>=1.11.1)
